spdb/__init__.py
spdb/debugger.py
simple_python_debugger-0.1.2.dist-info/METADATA
simple_python_debugger-0.1.2.dist-info/WHEEL
simple_python_debugger-0.1.2.dist-info/top_level.txt
simple_python_debugger-0.1.2.dist-info/RECORD
