Metadata-Version: 2.1
Name: simple-python-debugger
Version: 0.1.2
Summary: Simple Debugger for Python
Home-page: https://github.com/mzebin/simple-python-debugger/
Author: Mohammed Zebin
Author-email: <mohammed.zebin7@gmail.com>
License: MIT
Keywords: Python,Python3,Debugger
Platform: UNKNOWN
Classifier: Programming Language :: Python :: 3
Classifier: Operating System :: Unix
Classifier: Operating System :: MacOS :: MacOS X
Classifier: Operating System :: Microsoft :: Windows
